tool.py
testlib/__init__.py
testlib/func.py
biantai99999-1.0.1.dist-info/METADATA
biantai99999-1.0.1.dist-info/WHEEL
biantai99999-1.0.1.dist-info/top_level.txt
biantai99999-1.0.1.dist-info/RECORD
