Metadata-Version: 2.1
Name: biantai99999
Version: 1.0.1
Summary: this is a wonderful lib
Home-page: http://github.com
Author: lion
Author-email: 15ymluo@stu.edu.cn
License: UNKNOWN
Platform: UNKNOWN
